pymusepipe/__init__.py
pymusepipe/align_pipe.py
pymusepipe/check_pipe.py
pymusepipe/combine.py
pymusepipe/config_pipe.py
pymusepipe/create_sof.py
pymusepipe/cube_convolve.py
pymusepipe/emission_lines.py
pymusepipe/graph_musepipe.py
pymusepipe/graph_pipe.py
pymusepipe/graphcheck_pipe.py
pymusepipe/init_musepipe.py
pymusepipe/mpdaf_pipe.py
pymusepipe/muse_alignment.py
pymusepipe/musepipe.py
pymusepipe/prep_recipes_pipe.py
pymusepipe/recipes_pipe.py
pymusepipe/sof_pipe.py
pymusepipe/target_sample.py
pymusepipe/util_pipe.py
pymusepipe/version.py
pymusepipe-2.9.7.dist-info/LICENSE.txt
pymusepipe-2.9.7.dist-info/METADATA
pymusepipe-2.9.7.dist-info/WHEEL
pymusepipe-2.9.7.dist-info/top_level.txt
pymusepipe-2.9.7.dist-info/RECORD
