Metadata-Version: 2.1
Name: pymusepipe
Version: 2.9.7
Summary: python module to reduce MUSE Raw data and combine them
Home-page: https://github.com/emsellem/pipemusepipe
Author: Eric Emsellem
Author-email: eric.emsellem@eso.org
License: MIT
Download-URL: https://github.com/emsellem/pymusepipe/archive/v2.9.6.beta.tar.gz
Keywords: MUSE,DATAREDUCTION
Platform: UNKNOWN
Classifier: Programming Language :: Python :: 3
Classifier: License :: OSI Approved :: MIT License
Classifier: Operating System :: OS Independent
Requires-Dist: mpdaf
Requires-Dist: numpy
Requires-Dist: scipy
Requires-Dist: astropy
